bufr_tools/CountryCodes.h
bufr_tools/Descriptor.cpp
bufr_tools/Descriptor.h
bufr_tools/ESOHBufr.cpp
bufr_tools/ESOHBufr.h
bufr_tools/LogBuffer.cpp
bufr_tools/LogBuffer.h
bufr_tools/LogEntry.cpp
bufr_tools/LogEntry.h
bufr_tools/Makefile
bufr_tools/Makefile.e-soh
bufr_tools/NorBufr.cpp
bufr_tools/NorBufr.h
bufr_tools/NorBufrIO.cpp
bufr_tools/NorBufrIO.h
bufr_tools/Oscar.cpp
bufr_tools/Oscar.h
bufr_tools/Sections.cpp
bufr_tools/Sections.h
bufr_tools/Tables.cpp
bufr_tools/Tables.h
bufr_tools/WSI.cpp
bufr_tools/WSI.h
bufr_tools/__init__.py
bufr_tools/_version.py
bufr_tools/bufr2txt.py
bufr_tools/bufresohmsg_py.cpp
bufr_tools/bufresohmsg_py.cpython-312-i386-linux-gnu.so
bufr_tools/bufresohmsg_py.h
bufr_tools/covjson2bufr.cpp
bufr_tools/covjson2bufr.h
bufr_tools/covjson2bufr.py
bufr_tools/create_mqtt_message_from_bufr.py
bufr_tools/create_mqtt_message_from_radar_bufr.py
bufr_tools/getenvvalue.py
bufr_tools/gettimeofday.cpp
bufr_tools/radar_cf.py
bufr_tools/data/oscar/oscar_stations_all.json
bufr_tools/data/oscar/oscar_stations_all_20230919.json
bufr_tools/data/oscar/oscar_stations_all_20240319.json
bufr_tools/data/oscar/oscar_stations_all_20251027.json
bufr_tools/data/schemas/bufr_to_e_soh_message.json
bufr_tools/data/tables/opera/bmtab_247.csv
bufr_tools/data/tables/opera/bmtab_65535.csv
bufr_tools/data/tables/opera/btc085.019
bufr_tools/data/tables/opera/bufrtabb_11.csv
bufr_tools/data/tables/opera/bufrtabb_12.csv
bufr_tools/data/tables/opera/bufrtabb_13.csv
bufr_tools/data/tables/opera/bufrtabb_14.csv
bufr_tools/data/tables/opera/bufrtabb_15.csv
bufr_tools/data/tables/opera/bufrtabb_16.csv
bufr_tools/data/tables/opera/bufrtabb_2.csv
bufr_tools/data/tables/opera/bufrtabb_6.csv
bufr_tools/data/tables/opera/bufrtabd_11.csv
bufr_tools/data/tables/opera/bufrtabd_12.csv
bufr_tools/data/tables/opera/bufrtabd_13.csv
bufr_tools/data/tables/opera/bufrtabd_14.csv
bufr_tools/data/tables/opera/bufrtabd_15.csv
rodeo_bufr_tools-0.4.0.dist-info/METADATA
rodeo_bufr_tools-0.4.0.dist-info/WHEEL
rodeo_bufr_tools-0.4.0.dist-info/top_level.txt
rodeo_bufr_tools-0.4.0.dist-info/RECORD
rodeo_bufr_tools-0.4.0.dist-info/licenses/LICENSE
