Metadata-Version: 2.4
Name: rodeo-bufr-tools
Version: 0.4.0
Summary: Tools for working with JSON-BUFR conversion in the E-SOH proejct.
Author: Istvan Sebök
Maintainer: Istavn Sebök, Amund Isaksen
Classifier: Programming Language :: Python :: 3
Classifier: Programming Language :: Python :: 3.11
Classifier: Programming Language :: Python :: Implementation :: CPython
Requires-Python: >=3.11
License-File: LICENSE
Requires-Dist: pybind11~=2.11.1
Dynamic: license-file
